odoo/addons/web_widget_timepicker/README.rst
odoo/addons/web_widget_timepicker/__init__.py
odoo/addons/web_widget_timepicker/__manifest__.py
odoo/addons/web_widget_timepicker/i18n/ca.po
odoo/addons/web_widget_timepicker/i18n/es.po
odoo/addons/web_widget_timepicker/i18n/pt_BR.po
odoo/addons/web_widget_timepicker/i18n/web_widget_timepicker.pot
odoo/addons/web_widget_timepicker/readme/CONTRIBUTORS.rst
odoo/addons/web_widget_timepicker/readme/CREDITS.rst
odoo/addons/web_widget_timepicker/readme/DESCRIPTION.rst
odoo/addons/web_widget_timepicker/readme/USAGE.rst
odoo/addons/web_widget_timepicker/static/description/icon.png
odoo/addons/web_widget_timepicker/static/description/index.html
odoo/addons/web_widget_timepicker/static/src/js/web_widget_timepicker.js
odoo/addons/web_widget_timepicker/views/web_widget_timepicker_assets.xml
odoo12_addon_web_widget_timepicker-12.0.1.0.1.dist-info/METADATA
odoo12_addon_web_widget_timepicker-12.0.1.0.1.dist-info/WHEEL
odoo12_addon_web_widget_timepicker-12.0.1.0.1.dist-info/top_level.txt
odoo12_addon_web_widget_timepicker-12.0.1.0.1.dist-info/RECORD
